logment/__init__.py
logment-0.0.4.dist-info/DESCRIPTION.rst
logment-0.0.4.dist-info/METADATA
logment-0.0.4.dist-info/RECORD
logment-0.0.4.dist-info/WHEEL
logment-0.0.4.dist-info/metadata.json
logment-0.0.4.dist-info/top_level.txt
